{"licenses":[{"name":"","id":0,"url":""}],"info":{"contributor":"","date_created":"","description":"","url":"","version":"","year":""},"categories":[{"id":1,"name":"title","supercategory":""},{"id":2,"name":"canvas","supercategory":""},{"id":3,"name":"x-labels","supercategory":""},{"id":4,"name":"y-labels","supercategory":""},{"id":5,"name":"x-title","supercategory":""},{"id":6,"name":"y-title","supercategory":""},{"id":7,"name":"legend","supercategory":""}],"images":[{"id":1,"width":630,"height":538,"file_name":"barChart1.jpg","license":0,"flickr_url":"","coco_url":"","date_captured":0},{"id":2,"width":372,"height":312,"file_name":"barChart10.png","license":0,"flickr_url":"","coco_url":"","date_captured":0},{"id":3,"width":1310,"height":595,"file_name":"barChart11.png","license":0,"flickr_url":"","coco_url":"","date_captured":0},{"id":4,"width":267,"height":189,"file_name":"barChart2.png","license":0,"flickr_url":"","coco_url":"","date_captured":0},{"id":5,"width":275,"height":183,"file_name":"barChart3.png","license":0,"flickr_url":"","coco_url":"","date_captured":0},{"id":6,"width":855,"height":535,"file_name":"barChart4.png","license":0,"flickr_url":"","coco_url":"","date_captured":0},{"id":7,"width":780,"height":420,"file_name":"barChart5.jpg","license":0,"flickr_url":"","coco_url":"","date_captured":0},{"id":8,"width":584,"height":338,"file_name":"barChart6.jpg","license":0,"flickr_url":"","coco_url":"","date_captured":0},{"id":9,"width":918,"height":669,"file_name":"barChart7.png","license":0,"flickr_url":"","coco_url":"","date_captured":0},{"id":10,"width":1137,"height":698,"file_name":"barChart8.png","license":0,"flickr_url":"","coco_url":"","date_captured":0},{"id":11,"width":1600,"height":1200,"file_name":"barChart9.png","license":0,"flickr_url":"","coco_url":"","date_captured":0}],"annotations":[{"id":1,"image_id":1,"category_id":1,"segmentation":[],"area":10589.0295,"bbox":[204.99,10.84,234.53,45.15],"iscrowd":0,"attributes":{"occluded":false,"rotation":0.0}},{"id":2,"image_id":1,"category_id":2,"segmentation":[],"area":208841.935,"bbox":[69.36,108.62,530.5,393.67],"iscrowd":0,"attributes":{"occluded":false,"rotation":0.0}},{"id":3,"image_id":1,"category_id":3,"segmentation":[],"area":11603.54999999998,"bbox":[122.97,508.23,449.75,25.8],"iscrowd":0,"attributes":{"occluded":false,"rotation":0.0}},{"id":4,"image_id":1,"category_id":4,"segmentation":[],"area":10644.564600000003,"bbox":[42.22,99.98,25.79,412.74],"iscrowd":0,"attributes":{"occluded":false,"rotation":0.0}},{"id":5,"image_id":1,"category_id":6,"segmentation":[],"area":2921.491200000001,"bbox":[4.09,252.51,25.79,113.28],"iscrowd":0,"attributes":{"occluded":false,"rotation":0.0}},{"id":6,"image_id":2,"category_id":1,"segmentation":[],"area":2489.8443000000007,"bbox":[122.01,5.91,153.41,16.23],"iscrowd":0,"attributes":{"occluded":false,"rotation":0.0}},{"id":7,"image_id":2,"category_id":4,"segmentation":[],"area":5822.661000000001,"bbox":[26.86,28.77,22.49,258.9],"iscrowd":0,"attributes":{"occluded":false,"rotation":0.0}},{"id":8,"image_id":2,"category_id":3,"segmentation":[],"area":4113.978000000006,"bbox":[87.71,286.56,247.83,16.6],"iscrowd":0,"attributes":{"occluded":false,"rotation":0.0}},{"id":9,"image_id":2,"category_id":2,"segmentation":[],"area":76300.218,"bbox":[54.88,22.14,294.3,259.26],"iscrowd":0,"attributes":{"occluded":false,"rotation":0.0}},{"id":10,"image_id":3,"category_id":4,"segmentation":[],"area":47775.5553,"bbox":[207.07,174.56,158.57,301.29],"iscrowd":0,"attributes":{"occluded":false,"rotation":0.0}},{"id":11,"image_id":3,"category_id":3,"segmentation":[],"area":21570.56539999997,"bbox":[361.24,493.56,722.39,29.86],"iscrowd":0,"attributes":{"occluded":false,"rotation":0.0}},{"id":12,"image_id":3,"category_id":5,"segmentation":[],"area":1235.846600000005,"bbox":[623.77,527.04,51.97,23.78],"iscrowd":0,"attributes":{"occluded":false,"rotation":0.0}},{"id":13,"image_id":3,"category_id":6,"segmentation":[],"area":3041.485200000001,"bbox":[151.57,299.75,43.16,70.47],"iscrowd":0,"attributes":{"occluded":false,"rotation":0.0}},{"id":14,"image_id":3,"category_id":7,"segmentation":[],"area":12000.416299999997,"bbox":[249.35,133.24,369.13,32.51],"iscrowd":0,"attributes":{"occluded":false,"rotation":0.0}},{"id":15,"image_id":3,"category_id":1,"segmentation":[],"area":15920.276799999996,"bbox":[490.74,55.72,323.32,49.24],"iscrowd":0,"attributes":{"occluded":false,"rotation":0.0}},{"id":16,"image_id":3,"category_id":2,"segmentation":[],"area":219571.5654,"bbox":[369.17,180.82,716.22,306.57],"iscrowd":0,"attributes":{"occluded":false,"rotation":0.0}},{"id":17,"image_id":4,"category_id":6,"segmentation":[],"area":371.1428,"bbox":[4.59,92.39,11.62,31.94],"iscrowd":0,"attributes":{"occluded":false,"rotation":0.0}},{"id":18,"image_id":4,"category_id":1,"segmentation":[],"area":683.0160000000002,"bbox":[174.6,25.59,76.4,8.94],"iscrowd":0,"attributes":{"occluded":false,"rotation":0.0}},{"id":19,"image_id":4,"category_id":2,"segmentation":[],"area":23243.2132,"bbox":[56.42,46.14,200.84,115.73],"iscrowd":0,"attributes":{"occluded":false,"rotation":0.0}},{"id":20,"image_id":4,"category_id":3,"segmentation":[],"area":2043.8696000000002,"bbox":[53.52,164.77,198.82,10.28],"iscrowd":0,"attributes":{"occluded":false,"rotation":0.0}},{"id":21,"image_id":4,"category_id":4,"segmentation":[],"area":3577.8600000000006,"bbox":[17.32,57.54,35.75,100.08],"iscrowd":0,"attributes":{"occluded":false,"rotation":0.0}},{"id":22,"image_id":4,"category_id":5,"segmentation":[],"area":812.7434999999987,"bbox":[110.93,176.61,80.87,10.05],"iscrowd":0,"attributes":{"occluded":false,"rotation":0.0}},{"id":23,"image_id":4,"category_id":1,"segmentation":[],"area":1447.1599999999999,"bbox":[83.9,8.39,101.2,14.3],"iscrowd":0,"attributes":{"occluded":false,"rotation":0.0}},{"id":24,"image_id":5,"category_id":6,"segmentation":[],"area":1911.6513,"bbox":[0.0,23.22,15.27,125.19],"iscrowd":0,"attributes":{"occluded":false,"rotation":0.0}},{"id":25,"image_id":5,"category_id":4,"segmentation":[],"area":3443.8257,"bbox":[13.82,11.08,23.13,148.89],"iscrowd":0,"attributes":{"occluded":false,"rotation":0.0}},{"id":26,"image_id":5,"category_id":3,"segmentation":[],"area":6659.004800000001,"bbox":[40.42,153.32,224.36,29.68],"iscrowd":0,"attributes":{"occluded":false,"rotation":0.0}},{"id":27,"image_id":5,"category_id":2,"segmentation":[],"area":32577.645200000006,"bbox":[38.98,13.97,234.76,138.77],"iscrowd":0,"attributes":{"occluded":false,"rotation":0.0}},{"id":28,"image_id":5,"category_id":1,"segmentation":[],"area":1832.5405,"bbox":[81.76,0.09,113.05,16.21],"iscrowd":0,"attributes":{"occluded":false,"rotation":0.0}},{"id":29,"image_id":6,"category_id":4,"segmentation":[],"area":15346.507099999999,"bbox":[38.07,81.43,39.73,386.27],"iscrowd":0,"attributes":{"occluded":false,"rotation":0.0}},{"id":30,"image_id":6,"category_id":6,"segmentation":[],"area":7194.558800000002,"bbox":[4.26,164.26,32.12,223.99],"iscrowd":0,"attributes":{"occluded":false,"rotation":0.0}},{"id":31,"image_id":6,"category_id":2,"segmentation":[],"area":266610.2308000001,"bbox":[77.8,91.57,720.14,370.22],"iscrowd":0,"attributes":{"occluded":false,"rotation":0.0}},{"id":32,"image_id":6,"category_id":1,"segmentation":[],"area":21094.6494,"bbox":[13.56,7.89,437.83,48.18],"iscrowd":0,"attributes":{"occluded":false,"rotation":0.0}},{"id":33,"image_id":6,"category_id":3,"segmentation":[],"area":21785.894400000023,"bbox":[92.16,466.01,696.48,31.28],"iscrowd":0,"attributes":{"occluded":false,"rotation":0.0}},{"id":34,"image_id":6,"category_id":5,"segmentation":[],"area":1510.9224000000024,"bbox":[417.58,499.82,61.62,24.52],"iscrowd":0,"attributes":{"occluded":false,"rotation":0.0}},{"id":35,"image_id":7,"category_id":2,"segmentation":[],"area":215762.74719999998,"bbox":[144.4,25.14,626.78,344.24],"iscrowd":0,"attributes":{"occluded":false,"rotation":0.0}},{"id":36,"image_id":7,"category_id":4,"segmentation":[],"area":42174.75,"bbox":[9.79,42.67,132.5,318.3],"iscrowd":0,"attributes":{"occluded":false,"rotation":0.0}},{"id":37,"image_id":7,"category_id":3,"segmentation":[],"area":15642.994800000006,"bbox":[138.79,384.8,619.77,25.24],"iscrowd":0,"attributes":{"occluded":false,"rotation":0.0}},{"id":38,"image_id":8,"category_id":1,"segmentation":[],"area":12569.338999999998,"bbox":[90.0,5.25,398.9,31.51],"iscrowd":0,"attributes":{"occluded":false,"rotation":0.0}},{"id":39,"image_id":8,"category_id":2,"segmentation":[],"area":98811.2062,"bbox":[78.78,58.65,496.09,199.18],"iscrowd":0,"attributes":{"occluded":false,"rotation":0.0}},{"id":40,"image_id":8,"category_id":3,"segmentation":[],"area":13721.821000000005,"bbox":[82.52,269.05,484.87,28.3],"iscrowd":0,"attributes":{"occluded":false,"rotation":0.0}},{"id":41,"image_id":8,"category_id":4,"segmentation":[],"area":6912.8137000000015,"bbox":[40.87,46.9,30.97,223.21],"iscrowd":0,"attributes":{"occluded":false,"rotation":0.0}},{"id":42,"image_id":8,"category_id":5,"segmentation":[],"area":1368.7488000000017,"bbox":[290.78,304.82,64.08,21.36],"iscrowd":0,"attributes":{"occluded":false,"rotation":0.0}},{"id":43,"image_id":8,"category_id":6,"segmentation":[],"area":4116.5088000000005,"bbox":[10.96,80.01,27.24,151.12],"iscrowd":0,"attributes":{"occluded":false,"rotation":0.0}},{"id":44,"image_id":9,"category_id":7,"segmentation":[],"area":17165.171299999995,"bbox":[528.26,54.13,330.29,51.97],"iscrowd":0,"attributes":{"occluded":false,"rotation":0.0}},{"id":45,"image_id":9,"category_id":4,"segmentation":[],"area":19865.9025,"bbox":[49.71,126.13,41.75,475.83],"iscrowd":0,"attributes":{"occluded":false,"rotation":0.0}},{"id":46,"image_id":9,"category_id":2,"segmentation":[],"area":338315.9494,"bbox":[91.99,133.52,732.46,461.89],"iscrowd":0,"attributes":{"occluded":false,"rotation":0.0}},{"id":47,"image_id":9,"category_id":1,"segmentation":[],"area":5414.7795,"bbox":[85.65,47.91,138.45,39.11],"iscrowd":0,"attributes":{"occluded":false,"rotation":0.0}},{"id":48,"image_id":10,"category_id":7,"segmentation":[],"area":19425.547199999997,"bbox":[27.37,12.76,515.54,37.68],"iscrowd":0,"attributes":{"occluded":false,"rotation":0.0}},{"id":49,"image_id":10,"category_id":2,"segmentation":[],"area":595276.7328,"bbox":[70.56,72.49,1034.76,575.28],"iscrowd":0,"attributes":{"occluded":false,"rotation":0.0}},{"id":50,"image_id":10,"category_id":3,"segmentation":[],"area":35727.31259999999,"bbox":[153.27,655.12,904.26,39.51],"iscrowd":0,"attributes":{"occluded":false,"rotation":0.0}},{"id":51,"image_id":10,"category_id":4,"segmentation":[],"area":38284.4216,"bbox":[4.4,57.79,63.41,603.76],"iscrowd":0,"attributes":{"occluded":false,"rotation":0.0}},{"id":52,"image_id":11,"category_id":2,"segmentation":[],"area":819803.07,"bbox":[328.66,192.63,1128.04,726.75],"iscrowd":0,"attributes":{"occluded":false,"rotation":0.0}},{"id":53,"image_id":11,"category_id":3,"segmentation":[],"area":66309.5829,"bbox":[387.11,941.5,1023.77,64.77],"iscrowd":0,"attributes":{"occluded":false,"rotation":0.0}},{"id":54,"image_id":11,"category_id":4,"segmentation":[],"area":55948.132300000005,"bbox":[216.33,214.75,75.83,737.81],"iscrowd":0,"attributes":{"occluded":false,"rotation":0.0}},{"id":55,"image_id":11,"category_id":5,"segmentation":[],"area":75130.67519999994,"bbox":[567.22,1025.23,552.96,135.87],"iscrowd":0,"attributes":{"occluded":false,"rotation":0.0}},{"id":56,"image_id":11,"category_id":6,"segmentation":[],"area":88414.16189999999,"bbox":[63.24,228.97,140.61,628.79],"iscrowd":0,"attributes":{"occluded":false,"rotation":0.0}}]}